csvtex/__init__.py
csvtex/main.py
csvtex-1.0.4.dist-info/LICENSE
csvtex-1.0.4.dist-info/METADATA
csvtex-1.0.4.dist-info/WHEEL
csvtex-1.0.4.dist-info/RECORD
