Metadata-Version: 2.1
Name: csvtex
Version: 1.0.4
Summary: Convert CSV Files to LaTeX Tables
License: MIT
Author: Scott Suk
Author-email: scottsuk0306@gmail.com
Requires-Python: >3.7
Classifier: License :: OSI Approved :: MIT License
Classifier: Programming Language :: Python :: 3
Classifier: Programming Language :: Python :: 3.8
Classifier: Programming Language :: Python :: 3.9
Classifier: Programming Language :: Python :: 3.10
Classifier: Programming Language :: Python :: 3.11
Classifier: Programming Language :: Python :: 3.12
Requires-Dist: pandas (>=2.2.2,<3.0.0)
